django_jinja_knockout/__init__.py
django_jinja_knockout/admin.py
django_jinja_knockout/apps.py
django_jinja_knockout/automation.py
django_jinja_knockout/contenttypes.py
django_jinja_knockout/context_processors.py
django_jinja_knockout/decorators.py
django_jinja_knockout/http.py
django_jinja_knockout/jinja2.py
django_jinja_knockout/log.py
django_jinja_knockout/managers.py
django_jinja_knockout/middleware.py
django_jinja_knockout/models.py
django_jinja_knockout/obj_dict.py
django_jinja_knockout/query.py
django_jinja_knockout/serializers.py
django_jinja_knockout/testing.py
django_jinja_knockout/testing_components.py
django_jinja_knockout/tpl.py
django_jinja_knockout/urls.py
django_jinja_knockout/validators.py
django_jinja_knockout/viewmodels.py
django_jinja_knockout/widgets.py
django_jinja_knockout/_allauth/__init__.py
django_jinja_knockout/_allauth/urls.py
django_jinja_knockout/_allauth/views.py
django_jinja_knockout/_allauth/jinja2/already_logged_in.htm
django_jinja_knockout/_allauth/jinja2/email.htm
django_jinja_knockout/_allauth/jinja2/email_confirm.htm
django_jinja_knockout/_allauth/jinja2/home.htm
django_jinja_knockout/_allauth/jinja2/login.htm
django_jinja_knockout/_allauth/jinja2/logout.htm
django_jinja_knockout/_allauth/jinja2/password_reset.htm
django_jinja_knockout/_allauth/jinja2/password_reset_done.htm
django_jinja_knockout/_allauth/jinja2/password_reset_from_key.htm
django_jinja_knockout/_allauth/jinja2/password_reset_from_key_done.htm
django_jinja_knockout/_allauth/jinja2/signup.htm
django_jinja_knockout/_allauth/jinja2/verification_sent.htm
django_jinja_knockout/field_filters/base.py
django_jinja_knockout/field_filters/choices.py
django_jinja_knockout/field_filters/range.py
django_jinja_knockout/forms/__init__.py
django_jinja_knockout/forms/base.py
django_jinja_knockout/forms/renderers.py
django_jinja_knockout/forms/validators.py
django_jinja_knockout/forms/vm_renderers.py
django_jinja_knockout/jinja2/base_bottom_scripts.htm
django_jinja_knockout-2.2.1.dist-info/AUTHORS.rst
django_jinja_knockout-2.2.1.dist-info/LICENSE
django_jinja_knockout-2.2.1.dist-info/METADATA
django_jinja_knockout-2.2.1.dist-info/WHEEL
django_jinja_knockout-2.2.1.dist-info/top_level.txt
django_jinja_knockout-2.2.1.dist-info/RECORD
