Metadata-Version: 2.1
Name: django-jinja-knockout
Version: 2.2.1
Summary: Django AJAX ModelForms. Read-only display ModelForms. Django AJAX datatables with CRUD and custom actions. Supports Django Templates.
Home-page: https://github.com/Dmitri-Sintsov/django-jinja-knockout
Author: Dmitriy Sintsov
Author-email: questpc256@gmail.com
License: LGPL-3.0
Keywords: django,jinja,knockout.js,ajax,forms,datatable,datatables,datagrid
Classifier: Development Status :: 5 - Production/Stable
Classifier: Environment :: Web Environment
Classifier: Framework :: Django
Classifier: Intended Audience :: Developers
Classifier: License :: OSI Approved :: BSD License
Classifier: Operating System :: OS Independent
Classifier: Programming Language :: Python :: 3
Classifier: Topic :: Internet :: WWW/HTTP :: Dynamic Content
License-File: LICENSE
License-File: AUTHORS.rst
Requires-Dist: django >=4.2.0
Requires-Dist: Jinja2
Requires-Dist: bleach
Requires-Dist: ensure >=1.0.4
Requires-Dist: lxml
Requires-Dist: sqlparse >0.4.3
Requires-Dist: pytz
